deep_layers/README.md
deep_layers/__init__.py
deep_layers/core/util_gcn.py
deep_layers/tf/graph/__init__.py
deep_layers/tf/graph/gcn.py
deep_layers/tf/graph/ntn.py
deep_layers/tf/graph/pointnet.py
deep_layers/tf/graph/set_transformer.py
deep_layers/tf/graph/sgr.py
deep_layers/tf/scientific/__init__.py
deep_layers/tf/scientific/coral.py
deep_layers/tf/scientific/deeponet.py
deep_layers/tf/scientific/deq.py
deep_layers/tf/scientific/hyperlayer.py
deep_layers/tf/scientific/kan.py
deep_layers/tf/scientific/neural_ode.py
deep_layers/tf/scientific/phycrnet.py
deep_layers/tf/scientific/piratenet.py
deep_layers/tf/scientific/sparse_memory.py
deep_layers/tf/scientific/steerable_conv.py
deep_layers/tf/scientific/vq.py
deep_layers/tf/sequence/__init__.py
deep_layers/tf/sequence/hyena.py
deep_layers/tf/sequence/linear_attention.py
deep_layers/tf/sequence/mamba.py
deep_layers/tf/sequence/retention.py
deep_layers/tf/vision/__init__.py
deep_layers/tf/vision/coord_conv.py
deep_layers/tf/vision/dropblock.py
deep_layers/tf/vision/glu.py
deep_layers/tf/vision/involution.py
deep_layers/torch/graph/__init__.py
deep_layers/torch/graph/gcn.py
deep_layers/torch/graph/ntn.py
deep_layers/torch/graph/pointnet.py
deep_layers/torch/graph/set_transformer.py
deep_layers/torch/graph/sgr.py
deep_layers/torch/scientific/__init__.py
deep_layers/torch/scientific/coral.py
deep_layers/torch/scientific/deeponet.py
deep_layers/torch/scientific/deq.py
deep_layers/torch/scientific/hyperlayer.py
deep_layers/torch/scientific/kan.py
deep_layers/torch/scientific/neural_ode.py
deep_layers/torch/scientific/phycrnet.py
deep_layers/torch/scientific/piratenet.py
deep_layers/torch/scientific/sparse_memory.py
deep_layers/torch/scientific/steerable_conv.py
deep_layers/torch/scientific/vq.py
deep_layers/torch/sequence/__init__.py
deep_layers/torch/sequence/hyena.py
deep_layers/torch/sequence/linear_attention.py
deep_layers/torch/sequence/mamba.py
deep_layers/torch/sequence/retention.py
deep_layers-0.1.0.dist-info/METADATA
deep_layers-0.1.0.dist-info/WHEEL
deep_layers-0.1.0.dist-info/licenses/LICENSE
deep_layers-0.1.0.dist-info/RECORD
