Metadata-Version: 2.4
Name: deep_layers
Version: 0.1.0
Summary: A Python library for novel and experimental deep learning layers.
Project-URL: Homepage, https://github.com/kuslavicek/deep_layers
Project-URL: Issues, https://github.com/kuslavicek/deep_layers/issues
Author-email: kuslavicek <kuslavicek@gmail.com>
License: MIT
License-File: LICENSE
Classifier: Intended Audience :: Science/Research
Classifier: License :: OSI Approved :: MIT License
Classifier: Programming Language :: Python :: 3
Classifier: Topic :: Scientific/Engineering :: Artificial Intelligence
Requires-Python: >=3.8
Provides-Extra: all
Requires-Dist: tensorflow>=2.10.0; extra == 'all'
Requires-Dist: torch>=2.0.0; extra == 'all'
Provides-Extra: tf
Requires-Dist: tensorflow>=2.10.0; extra == 'tf'
Provides-Extra: torch
Requires-Dist: torch>=2.0.0; extra == 'torch'
